{
  "contents": [
    {
      "id": 15,
      "label": "title",
      "text": "Evolution of concepts in epilepsy surgery *",
      "parent_id": 0,
      "order": 0
    },
    {
      "id": 27,
      "label": "section-title",
      "text": "Early epilepsy surgery",
      "parent_id": 27,
      "order": 1
    },
    {
      "id": 40,
      "label": "section-title",
      "text": "Early epilepsy surgery and the ILAE",
      "parent_id": 40,
      "order": 2
    },
    {
      "id": 49,
      "label": "section-title",
      "text": "Stimulation， X-Ray， and EEG",
      "parent_id": 49,
      "order": 3
    },
    {
      "id": 62,
      "label": "section-title",
      "text": "Temporal lobe epilepsy",
      "parent_id": 62,
      "order": 4
    },
    {
      "id": 73,
      "label": "section-title",
      "text": "Midcentury epilepsy surgery and the ILAE",
      "parent_id": 73,
      "order": 5
    },
    {
      "id": 76,
      "label": "section-title",
      "text": "Temporal lobe epilepsy (continued)",
      "parent_id": 76,
      "order": 6
    },
    {
      "id": 93,
      "label": "section-title",
      "text": "Neuroimaging",
      "parent_id": 93,
      "order": 6
    },
    {
      "id": 104,
      "label": "section-title",
      "text": "Behavioral evaluations",
      "parent_id": 104,
      "order": 6
    },
    {
      "id": 115,
      "label": "section-title",
      "text": "Creation of an international epilepsy surgery community",
      "parent_id": 115,
      "order": 6
    },
    {
      "id": 136,
      "label": "section-title",
      "text": "21st century advances and challenges",
      "parent_id": 136,
      "order": 6
    },
    {
      "id": 159,
      "label": "section-title",
      "text": "Supplementary data",
      "parent_id": 159,
      "order": 6
    },
    {
      "id": 161,
      "label": "section-title",
      "text": "Acknowledgements and disclosures.",
      "parent_id": 161,
      "order": 6
    },
    {
      "id": 164,
      "label": "section-title",
      "text": "References",
      "parent_id": 164,
      "order": 6
    }
  ]
}