{
  "contents": [
    {
      "id": 2,
      "label": "title",
      "text": "Fighting Back Partnership Housing Voucher Program",
      "parent_id": 0,
      "order": 0
    },
    {
      "id": 4,
      "label": "section-title",
      "text": "RECITALS",
      "parent_id": 4,
      "order": 1
    },
    {
      "id": 63,
      "label": "section-title",
      "text": "EXHIBIT A SCHEDULE OF PAYMENTS",
      "parent_id": 63,
      "order": 2
    },
    {
      "id": 68,
      "label": "section-title",
      "text": "Exhibit B- Grant Agreement Monthly Report",
      "parent_id": 68,
      "order": 3
    },
    {
      "id": 77,
      "label": "section-title",
      "text": "Grantee Information",
      "parent_id": 77,
      "order": 4
    },
    {
      "id": 82,
      "label": "section-title",
      "text": "Award Details",
      "parent_id": 82,
      "order": 5
    },
    {
      "id": 84,
      "label": "section-title",
      "text": "Performance Measures& Outcomes",
      "parent_id": 84,
      "order": 6
    },
    {
      "id": 92,
      "label": "section-title",
      "text": "Grantee Representative Signature",
      "parent_id": 92,
      "order": 6
    },
    {
      "id": 97,
      "label": "section-title",
      "text": "EXHIBIT C INSURANCE REQUIREMENTS",
      "parent_id": 97,
      "order": 6
    }
  ]
}