{
  "contents": [
    {
      "id": 2,
      "label": "title",
      "text": "r Vision of Criminal Justic e",
      "parent_id": 0,
      "order": 0
    },
    {
      "id": 19,
      "label": "section-title",
      "text": "IN T H I S I SS U E",
      "parent_id": 19,
      "order": 1
    },
    {
      "id": 34,
      "label": "section-title",
      "text": "CJ I S Gove r n i ng B oa r d",
      "parent_id": 34,
      "order": 2
    },
    {
      "id": 77,
      "label": "title",
      "text": "CJIS Program Overview",
      "parent_id": 0,
      "order": 3
    },
    {
      "id": 101,
      "label": "title",
      "text": "CISS Project Management Updates",
      "parent_id": 0,
      "order": 4
    },
    {
      "id": 103,
      "label": "section-title",
      "text": "Wave 0 V 1.5",
      "parent_id": 103,
      "order": 5
    },
    {
      "id": 107,
      "label": "section-title",
      "text": "IN BRIEF",
      "parent_id": 107,
      "order": 6
    },
    {
      "id": 119,
      "label": "section-title",
      "text": "CISS Informatoin Sharing — Searches vs. IEs",
      "parent_id": 119,
      "order": 6
    },
    {
      "id": 125,
      "label": "section-title",
      "text": "Lessons Learned",
      "parent_id": 125,
      "order": 6
    },
    {
      "id": 137,
      "label": "title",
      "text": "<unk>",
      "parent_id": 137,
      "order": 6
    },
    {
      "id": 146,
      "label": "section-title",
      "text": "IN BRIEF",
      "parent_id": 146,
      "order": 6
    },
    {
      "id": 147,
      "label": "section-title",
      "text": "JUST FINISHED",
      "parent_id": 147,
      "order": 6
    },
    {
      "id": 150,
      "label": "section-title",
      "text": "NEXT MONTH",
      "parent_id": 150,
      "order": 6
    },
    {
      "id": 156,
      "label": "section-title",
      "text": "2013 CISS Monthly Status Meetings",
      "parent_id": 156,
      "order": 6
    },
    {
      "id": 170,
      "label": "section-title",
      "text": "Namin g Conventions for Wav e s and Release s",
      "parent_id": 170,
      "order": 6
    },
    {
      "id": 176,
      "label": "section-title",
      "text": "CIDRIS Updat e Connecticut Impaired Driver Reco r d s System",
      "parent_id": 176,
      "order": 6
    },
    {
      "id": 183,
      "label": "section-title",
      "text": "OBTS Updat e Offend e r-B a sed Trac k ing System",
      "parent_id": 183,
      "order": 6
    },
    {
      "id": 220,
      "label": "title",
      "text": "<unk>",
      "parent_id": 0,
      "order": 6
    },
    {
      "id": 222,
      "label": "section-title",
      "text": "<unk>",
      "parent_id": 222,
      "order": 6
    },
    {
      "id": 225,
      "label": "section-title",
      "text": "PSDN Rollout",
      "parent_id": 225,
      "order": 6
    }
  ]
}