{
  "contents": [
    {
      "id": 4,
      "label": "title",
      "text": "36YAPI-TURKEYBUILD Istanbul Will once again be the gathering point for international building professionals seeking innovation and opportunities in global markets",
      "parent_id": 0,
      "order": 0
    },
    {
      "id": 13,
      "label": "section-title",
      "text": "Guest Country South Korea Project",
      "parent_id": 13,
      "order": 1
    },
    {
      "id": 23,
      "label": "section-title",
      "text": "●5th Eurasian Building Forum",
      "parent_id": 23,
      "order": 2
    },
    {
      "id": 28,
      "label": "section-title",
      "text": "Awards to be presented within the Scope of the Exhibition",
      "parent_id": 28,
      "order": 3
    }
  ]
}